{"generatedAt":"2026-06-29T02:08:34+09:00","source":"gorics-news-automation","page":"financial","categories":[{"id":"ai-infrastructure","name":"AI인프라","icon":"🧠","count":2},{"id":"energy-geopolitics","name":"에너지·지정학","icon":"🛢️","count":1},{"id":"semiconductors","name":"반도체","icon":"💾","count":2}],"total":5,"allItems":[{"id":"fin-20260629-0208-ft-bis-ai-exuberance","category":"ai-infrastructure","categoryName":"AI인프라","category_ko":"AI인프라","categoryIcon":"🧠","title":"BIS, AI 인프라 투자 과열이 긴 조정으로 이어질 위험 경고","publishedAt":"2026-06-28","date":"2026-06-28","source":"Financial Times","url":"https://www.ft.com/content/e81ce414-e4bd-4e8c-bac7-94f7bf17def4","description":"BIS는 빅테크·하이퍼스케일러의 AI 설비투자가 기대수익을 못 내면 부채와 주식시장 노출을 통해 장기 투자침체로 번질 수 있다고 경고했다.","score":184,"priority":184,"tags":["BIS","AI인프라","하이퍼스케일러","부채","버블"]},{"id":"fin-20260629-0208-reuters-firmus-nvidia","category":"ai-infrastructure","categoryName":"AI인프라","category_ko":"AI인프라","categoryIcon":"🧠","title":"Firmus-엔비디아 AI 접근 계약…GPU 공급·AI 클라우드 비용 경쟁 확대","publishedAt":"2026-06-28","date":"2026-06-28","source":"Reuters","url":"https://www.reuters.com/world/asia-pacific/australias-firmus-technologies-strikes-ai-access-deal-with-nvidia-2026-06-28/","description":"호주 Firmus가 엔비디아와 손잡고 신생 AI 기업에 더 낮은 비용의 컴퓨팅 자원을 제공하기로 하면서 AI 클라우드 수요와 GPU 공급망 경쟁이 이어진다.","score":178,"priority":178,"tags":["Nvidia","Firmus","GPU","AI클라우드","호주"]},{"id":"fin-20260629-0208-reuters-aramco-helicopter","category":"energy-geopolitics","categoryName":"에너지·지정학","category_ko":"에너지·지정학","categoryIcon":"🛢️","title":"아람코 헬기 추락, 라스 타누라 원유 터미널 재가동 국면의 운영 리스크 부각","publishedAt":"2026-06-28","date":"2026-06-28","source":"Reuters","url":"https://www.reuters.com/world/saudi-aramco-helicopter-crash-kills-14-state-new-agency-says-2026-06-28/","description":"사우디 라스 타누라에서 아람코 헬기 사고로 14명이 사망하면서 중동 에너지 인프라와 원유 수송 정상화 과정의 안전 리스크가 시장 변수로 떠올랐다.","score":172,"priority":172,"tags":["Aramco","라스타누라","사우디","원유터미널","운영리스크"]},{"id":"fin-20260629-0208-times-micron-ai-memory","category":"semiconductors","categoryName":"반도체","category_ko":"반도체","categoryIcon":"💾","title":"마이크론, AI HBM 수요로 고성장…메모리 가격 사이클의 중심으로 부상","publishedAt":"2026-06-28","date":"2026-06-28","source":"The Times","url":"https://www.thetimes.com/business/technology/article/micron-semiconductor-ai-stock-volatile-7ftpl8v2j","description":"HBM3E와 엔비디아 공급망 효과로 마이크론의 AI 메모리 지위가 커졌고, 제한된 공급은 DRAM 가격과 PC·맥북 등 소비재 비용에도 영향을 주고 있다.","score":166,"priority":166,"tags":["Micron","HBM","DRAM","Nvidia","메모리"]},{"id":"fin-20260629-0208-reuters-semi-selloff-ai-spending","category":"semiconductors","categoryName":"반도체","category_ko":"반도체","categoryIcon":"💾","title":"반도체주 급락, AI 설비투자 지속성 의심이 나스닥 조정 압력으로 확산","publishedAt":"2026-06-23","date":"2026-06-23","source":"Reuters","url":"https://www.reuters.com/business/nasdaq-futures-fall-2-tech-worries-fed-hike-bets-2026-06-23/","description":"투자자들이 부채로 조달되는 AI 투자와 금리 부담을 재평가하면서 필라델피아 반도체지수가 급락했고 기술주 중심 지수 변동성이 커졌다.","score":154,"priority":154,"tags":["반도체","나스닥","AI투자","금리","SOX"]}],"byCategory":{}}