{
  "generatedAt": "2026-06-25T18:33:13+09:00",
  "source": "gorics-news-automation",
  "page": "financial",
  "categories": [
    {"id":"global-markets","name":"글로벌시장","icon":"📈","count":2},
    {"id":"semiconductors","name":"반도체","icon":"💾","count":1},
    {"id":"ai-infrastructure","name":"AI 인프라","icon":"🤖","count":1},
    {"id":"energy-geopolitics","name":"에너지·지정학","icon":"🛢️","count":0},
    {"id":"fx-rates","name":"금리·환율","icon":"💱","count":0}
  ],
  "total": 4,
  "allItems": [
    {"id":"fin-20260625-1833-asia-stocks-micron-ai","category":"global-markets","categoryName":"글로벌시장","category_ko":"글로벌시장","categoryIcon":"📈","title":"아시아 증시 급등, AI 반도체 실적이 위험선호 회복","publishedAt":"2026-06-25","date":"2026-06-25","source":"Reuters","url":"https://www.reuters.com/world/china/global-markets-wrapup-1-2026-06-25/","description":"마이크론·퀄컴 전망이 AI 수요 불안을 완화하며 일본·한국 증시와 아시아 위험자산 전반을 끌어올렸다.","score":99,"priority":99,"tags":["아시아증시","AI반도체","마이크론","퀄컴","위험자산"]},
    {"id":"fin-20260625-1833-europe-shares-ai-oil","category":"global-markets","categoryName":"글로벌시장","category_ko":"글로벌시장","categoryIcon":"📊","title":"유럽 증시 상승, AI 랠리와 유가 안정이 동시 반영","publishedAt":"2026-06-25","date":"2026-06-25","source":"Reuters","url":"https://www.reuters.com/markets/europe/european-shares-gain-upbeat-micron-forecast-revives-ai-rally-2026-06-25/","description":"STOXX 600이 상승 출발했고 반도체·장비주가 강세를 보였다. 유가 하락은 인플레이션 부담 완화 재료로 작용했다.","score":96,"priority":96,"tags":["유럽증시","STOXX600","유가","ASML","인피니언"]},
    {"id":"fin-20260625-1833-korea-chip-shares","category":"semiconductors","categoryName":"반도체","category_ko":"반도체","categoryIcon":"💾","title":"한국 반도체주 급등, HBM 수요와 미국 상장 기대 부각","publishedAt":"2026-06-25","date":"2026-06-25","source":"Reuters","url":"https://www.reuters.com/world/asia-pacific/south-korean-chip-shares-rally-after-microns-upbeat-earnings-2026-06-25/","description":"SK하이닉스와 삼성전자가 마이크론 호실적 여파로 강세를 보였다. AI 메모리 체인의 밸류에이션 재평가가 이어지고 있다.","score":95,"priority":95,"tags":["SK하이닉스","삼성전자","HBM","메모리","KOSPI"]},
    {"id":"fin-20260625-1833-lingyi-hk-ipo-ai","category":"ai-infrastructure","categoryName":"AI 인프라","category_ko":"AI 인프라","categoryIcon":"🤖","title":"링이아이테크 홍콩 IPO, AI 서버·로봇 제조 투자 확대","publishedAt":"2026-06-25","date":"2026-06-25","source":"Reuters","url":"https://www.reuters.com/world/asia-pacific/apple-supplier-lingyi-itech-prices-106-billion-hong-kong-ipo-tap-ai-demand-2026-06-24/","description":"AI 서버와 휴머노이드, 광통신 부품 투자가 IPO 자금의 핵심 용도다. 홍콩 IPO 시장과 AI 공급망 투자심리에 영향을 준다.","score":88,"priority":88,"tags":["홍콩IPO","AI서버","애플공급망","광통신","휴머노이드"]}
  ],
  "byCategory": {"global-markets": [],"semiconductors": [],"ai-infrastructure": [],"energy-geopolitics": [],"fx-rates": []}
}