{"generatedAt":"2026-06-21T17:10:21+09:00","source":"Latest public news overlay; current run items only for GitHub Pages news site","page":"main-latest-overlay-20260621-1710","categories":[{"id":"economy","name":"경제·금융","icon":"💹","count":2},{"id":"global","name":"국제","icon":"🌍","count":1},{"id":"politics","name":"정치","icon":"🏛️","count":1},{"id":"tech","name":"기술","icon":"🤖","count":2},{"id":"play","name":"스포츠·엔터","icon":"⚽","count":1},{"id":"culture","name":"문화","icon":"🎭","count":1}],"total":8,"allItems":[{"id":"latest-20260621-1710-dow-futures-hormuz-ai-chips","category":"economy","categoryName":"경제·금융","categoryIcon":"💹","title":"다우 선물 약세, 호르무즈 긴장과 AI 반도체 랠리 동시 주시","description":"이란의 호르무즈 폐쇄 주장과 새 미·이란 협상 기대가 맞물리며 선물이 약세를 보였다. 엔비디아·마이크론 등 AI 반도체주는 여전히 시장의 핵심 모멘텀으로 꼽혔다.","url":"https://www.investors.com/market-trend/stock-market-today/dow-jones-futures-nvidia-5-chips-buy-points-spacex-stock/","source":{"name":"Investor's Business Daily"},"publishedAt":"2026-06-21","score":218,"tags":["다우선물","호르무즈","엔비디아","마이크론","AI반도체"]},{"id":"latest-20260621-1710-france-heatwave-red-alert","category":"global","categoryName":"국제","categoryIcon":"🌍","title":"프랑스, 폭염 적색경보 속 야외 스포츠·공공 음주 제한","description":"프랑스 일부 지역 기온이 40도까지 오를 것으로 예상되면서 당국이 공공 음주와 야외 스포츠 행사를 제한했다. 파리 주요 관광지에는 냉각 설비가 설치됐고 산불 대비도 강화됐다.","url":"https://apnews.com/article/337471b5950543447c92010ca1081a8d","source":{"name":"AP"},"publishedAt":"2026-06-21","score":188,"tags":["프랑스","폭염","적색경보","기후","산불"]},{"id":"latest-20260621-1710-wells-fargo-sp500-target","category":"economy","categoryName":"경제·금융","categoryIcon":"💹","title":"웰스파고, 기업이익 개선에 S&P 500 연말 목표치 상향","description":"웰스파고가 기업 실적 전망 개선과 지정학 리스크 완화를 반영해 S&P 500 목표치를 높였다. AI·반도체와 경기민감 업종이 지수 상승 논리의 중심에 있다.","url":"https://www.reuters.com/business/wells-fargo-raises-sp-500-target-stronger-earnings-outlook-2026-06-16/","source":{"name":"Reuters"},"publishedAt":"2026-06-16","score":176,"tags":["S&P500","웰스파고","기업이익","AI","반도체"]},{"id":"latest-20260621-1710-china-ai-consumption-measures","category":"tech","categoryName":"기술","categoryIcon":"🤖","title":"중국, 소비재·서비스 AI 접목 17개 조치 발표","description":"중국 상무부가 가전·휴머노이드 로봇·공공서비스에 AI 적용을 확대하는 17개 조치를 내놨다. 내수 부양과 AI 산업 생태계 확대를 동시에 겨냥한 정책이다.","url":"https://www.reuters.com/business/media-telecom/china-announces-measures-promote-ai-integration-with-consumption-2026-06-18/","source":{"name":"Reuters"},"publishedAt":"2026-06-18","score":170,"tags":["중국","AI","소비","로봇","가전"]},{"id":"latest-20260621-1710-iran-worldcup-tijuana-fans","category":"play","categoryName":"스포츠·엔터","categoryIcon":"⚽","title":"이란 월드컵 대표팀, 티후아나 숙소서 팬 응원 속 미국 경기 준비","description":"정치·비자 제약으로 멕시코 티후아나에 머무는 이란 대표팀 숙소에 팬들이 모였다. 월드컵 현장에서 국제정치와 스포츠가 교차하는 장면이 부각됐다.","url":"https://apnews.com/article/29319fcd3d6a486c1d584231aefc7f0a","source":{"name":"AP"},"publishedAt":"2026-06-20","score":160,"tags":["월드컵","이란","티후아나","팬문화","비자"]},{"id":"latest-20260621-1710-us-politics-trump-ufc-ethics","category":"politics","categoryName":"정치","categoryIcon":"🏛️","title":"트럼프 백악관 UFC 생일 행사, 외교 홍보와 윤리 논란 동시 확산","description":"트럼프 대통령의 80세 생일·건국 250주년 행사가 이란 합의 홍보와 백악관 UFC 이벤트로 주목받았다. 행사 비용과 가족 관련 사업 이해충돌 논란도 이어졌다.","url":"https://apnews.com/article/82b8e51b557af2d54050d3ef9a069560","source":{"name":"AP"},"publishedAt":"2026-06-14","score":148,"tags":["트럼프","UFC","백악관","윤리","이란합의"]},{"id":"latest-20260621-1710-worldcup-faith-unity-culture","category":"culture","categoryName":"문화","categoryIcon":"🎭","title":"월드컵 대표팀, 사회 분열 속 신앙·다양성·연대 메시지 부각","description":"여러 월드컵 대표팀에서 종교와 배경이 다른 선수들이 공개적으로 신앙과 존중을 드러내고 있다. 스포츠가 사회적 분열 속 문화적 연대의 사례로 조명됐다.","url":"https://apnews.com/article/6413b6720693ee665882ab5ff9585d84","source":{"name":"AP"},"publishedAt":"2026-06-18","score":140,"tags":["월드컵","신앙","다양성","문화","연대"]},{"id":"latest-20260621-1710-nvidia-rtx-spark-ai-pc","category":"tech","categoryName":"기술","categoryIcon":"🤖","title":"엔비디아 RTX Spark, AI 기능을 PC 로컬 실행으로 확장","description":"엔비디아가 AI 작업을 노트북·데스크톱에서 직접 처리하는 PC용 칩을 공개했다. 클라우드 의존을 줄이고 개인용 AI 에이전트 시장을 키우려는 전략으로 해석된다.","url":"https://www.reuters.com/world/china/nvidia-ceo-kick-off-dominate-computex-gathering-taipei-2026-05-31/","source":{"name":"Reuters"},"publishedAt":"2026-05-31","score":136,"tags":["엔비디아","AI PC","RTX Spark","로컬AI","반도체"]}],"byCategory":{"economy":[],"global":[],"politics":[],"tech":[],"play":[],"culture":[]}}