[{"conclusion":"","createdAt":"2026-07-08T05:29:18Z","databaseId":28919858639,"event":"push","headSha":"1508b57fd7c75941125a3ee436de3ec107cb51e2","status":"in_progress","updatedAt":"2026-07-08T05:29:24Z","url":"https://github.com/gorics/website/actions/runs/28919858639"},{"conclusion":"failure","createdAt":"2026-07-08T05:26:14Z","databaseId":28919737997,"event":"push","headSha":"188673578d23af5e70b8e088323f543b255b8892","status":"completed","updatedAt":"2026-07-08T05:28:50Z","url":"https://github.com/gorics/website/actions/runs/28919737997"},{"conclusion":"failure","createdAt":"2026-07-08T05:23:18Z","databaseId":28919622947,"event":"workflow_dispatch","headSha":"a54f374d442f1611165fb7eaaf4e6848bc33027f","status":"completed","updatedAt":"2026-07-08T05:25:09Z","url":"https://github.com/gorics/website/actions/runs/28919622947"},{"conclusion":"failure","createdAt":"2026-07-08T05:21:41Z","databaseId":28919557409,"event":"workflow_dispatch","headSha":"deeb4564075e5ca7b605eaf4843f96f3cc42810d","status":"completed","updatedAt":"2026-07-08T05:23:48Z","url":"https://github.com/gorics/website/actions/runs/28919557409"},{"conclusion":"failure","createdAt":"2026-07-08T05:21:02Z","databaseId":28919531169,"event":"workflow_dispatch","headSha":"deeb4564075e5ca7b605eaf4843f96f3cc42810d","status":"completed","updatedAt":"2026-07-08T05:22:57Z","url":"https://github.com/gorics/website/actions/runs/28919531169"},{"conclusion":"failure","createdAt":"2026-07-08T05:13:01Z","databaseId":28919213053,"event":"push","headSha":"13538c9cf3f7e7e855185be80a363ca314a56e74","status":"completed","updatedAt":"2026-07-08T05:15:18Z","url":"https://github.com/gorics/website/actions/runs/28919213053"},{"conclusion":"failure","createdAt":"2026-07-08T05:06:11Z","databaseId":28918942493,"event":"push","headSha":"082bccfe3403137e58d44b16322498110653ecc4","status":"completed","updatedAt":"2026-07-08T05:07:54Z","url":"https://github.com/gorics/website/actions/runs/28918942493"},{"conclusion":"failure","createdAt":"2026-07-08T05:03:01Z","databaseId":28918814116,"event":"push","headSha":"2e06be5cb10d4c72a4eeee2c52705f39cbe93d1b","status":"completed","updatedAt":"2026-07-08T05:04:43Z","url":"https://github.com/gorics/website/actions/runs/28918814116"}]
